{"is_source_file": true, "format": "Python", "description": "This source file contains Django REST Framework serializers for models related to user profiles, bookings, and payment transactions, defining how data is serialized and validated in the backend API.", "external_files": ["rest_framework.serializers", "./models"], "external_methods": ["serializers.ModelSerializer", "serializers.StringRelatedField", "serializers.DecimalField", "serializers.PrimaryKeyRelatedField", "serializers.CharField", "serializers.BooleanField", "serializers.ValidationError", "UserProfile.objects.all()", "Booking.objects.all()"], "published": ["UserProfileSerializer", "BookingSerializer", "PaymentTransactionSerializer"], "classes": [{"name": "UserProfileSerializer", "description": "Serializer for the UserProfile model, exposing user details and wallet balance."}, {"name": "BookingSerializer", "description": "Serializer for the Booking model, including fields related to journey details, passenger info, and payment status. Contains a custom validate method for age and fare validation."}, {"name": "PaymentTransactionSerializer", "description": "Serializer for the PaymentTransaction model, linking to bookings and including transaction details."}], "methods": [{"name": "validate(self, data)", "description": "Validates passenger age and fare to ensure they are positive values.", "scope": "BookingSerializer", "scopeKind": "class"}], "calls": ["UserProfile.objects.all()", "Booking.objects.all()"], "search-terms": ["serializers", "UserProfileSerializer", "BookingSerializer", "PaymentTransactionSerializer", "DRF", "serializers.ModelSerializer", "validate", "payment", "booking", "user profile"], "state": 2, "file_id": 20, "knowledge_revision": 50, "git_revision": "756eef19971d9e96ddb6cf129a1482dffdc33ec4", "revision_history": [{"46": ""}, {"48": "756eef19971d9e96ddb6cf129a1482dffdc33ec4"}, {"50": "756eef19971d9e96ddb6cf129a1482dffdc33ec4"}], "ctags": [{"_type": "tag", "name": "BookingSerializer", "path": "/home/kavia/workspace/code-generation/quickbook-tatkal-21a702cc/backend/api/serializers.py", "pattern": "/^class BookingSerializer(serializers.ModelSerializer):$/", "language": "Python", "kind": "class"}, {"_type": "tag", "name": "Meta", "path": "/home/kavia/workspace/code-generation/quickbook-tatkal-21a702cc/backend/api/serializers.py", "pattern": "/^    class Meta:$/", "language": "Python", "kind": "class", "scope": "BookingSerializer", "scopeKind": "class"}, {"_type": "tag", "name": "Meta", "path": "/home/kavia/workspace/code-generation/quickbook-tatkal-21a702cc/backend/api/serializers.py", "pattern": "/^    class Meta:$/", "language": "Python", "kind": "class", "scope": "PaymentTransactionSerializer", "scopeKind": "class"}, {"_type": "tag", "name": "Meta", "path": "/home/kavia/workspace/code-generation/quickbook-tatkal-21a702cc/backend/api/serializers.py", "pattern": "/^    class Meta:$/", "language": "Python", "kind": "class", "scope": "UserProfileSerializer", "scopeKind": "class"}, {"_type": "tag", "name": "PaymentTransactionSerializer", "path": "/home/kavia/workspace/code-generation/quickbook-tatkal-21a702cc/backend/api/serializers.py", "pattern": "/^class PaymentTransactionSerializer(serializers.ModelSerializer):$/", "language": "Python", "kind": "class"}, {"_type": "tag", "name": "UserProfileSerializer", "path": "/home/kavia/workspace/code-generation/quickbook-tatkal-21a702cc/backend/api/serializers.py", "pattern": "/^class UserProfileSerializer(serializers.ModelSerializer):$/", "language": "Python", "kind": "class"}, {"_type": "tag", "name": "booking", "path": "/home/kavia/workspace/code-generation/quickbook-tatkal-21a702cc/backend/api/serializers.py", "pattern": "/^    booking = BookingSerializer(read_only=True)$/", "language": "Python", "kind": "variable", "scope": "PaymentTransactionSerializer", "scopeKind": "class"}, {"_type": "tag", "name": "booking_id", "path": "/home/kavia/workspace/code-generation/quickbook-tatkal-21a702cc/backend/api/serializers.py", "pattern": "/^    booking_id = serializers.PrimaryKeyRelatedField($/", "language": "Python", "kind": "variable", "scope": "PaymentTransactionSerializer", "scopeKind": "class"}, {"_type": "tag", "name": "fare", "path": "/home/kavia/workspace/code-generation/quickbook-tatkal-21a702cc/backend/api/serializers.py", "pattern": "/^    fare = serializers.DecimalField(max_digits=8, decimal_places=2)$/", "language": "Python", "kind": "variable", "scope": "BookingSerializer", "scopeKind": "class"}, {"_type": "tag", "name": "fields", "path": "/home/kavia/workspace/code-generation/quickbook-tatkal-21a702cc/backend/api/serializers.py", "pattern": "/^        fields = [$/", "language": "Python", "kind": "variable", "scope": "BookingSerializer.Meta", "scopeKind": "class"}, {"_type": "tag", "name": "fields", "path": "/home/kavia/workspace/code-generation/quickbook-tatkal-21a702cc/backend/api/serializers.py", "pattern": "/^        fields = [$/", "language": "Python", "kind": "variable", "scope": "PaymentTransactionSerializer.Meta", "scopeKind": "class"}, {"_type": "tag", "name": "fields", "path": "/home/kavia/workspace/code-generation/quickbook-tatkal-21a702cc/backend/api/serializers.py", "pattern": "/^        fields = [$/", "language": "Python", "kind": "variable", "scope": "UserProfileSerializer.Meta", "scopeKind": "class"}, {"_type": "tag", "name": "model", "path": "/home/kavia/workspace/code-generation/quickbook-tatkal-21a702cc/backend/api/serializers.py", "pattern": "/^        model = Booking$/", "language": "Python", "kind": "variable", "scope": "BookingSerializer.Meta", "scopeKind": "class"}, {"_type": "tag", "name": "model", "path": "/home/kavia/workspace/code-generation/quickbook-tatkal-21a702cc/backend/api/serializers.py", "pattern": "/^        model = PaymentTransaction$/", "language": "Python", "kind": "variable", "scope": "PaymentTransactionSerializer.Meta", "scopeKind": "class"}, {"_type": "tag", "name": "model", "path": "/home/kavia/workspace/code-generation/quickbook-tatkal-21a702cc/backend/api/serializers.py", "pattern": "/^        model = UserProfile$/", "language": "Python", "kind": "variable", "scope": "UserProfileSerializer.Meta", "scopeKind": "class"}, {"_type": "tag", "name": "paid", "path": "/home/kavia/workspace/code-generation/quickbook-tatkal-21a702cc/backend/api/serializers.py", "pattern": "/^    paid = serializers.BooleanField(read_only=True)$/", "language": "Python", "kind": "variable", "scope": "BookingSerializer", "scopeKind": "class"}, {"_type": "tag", "name": "paid_via_wallet", "path": "/home/kavia/workspace/code-generation/quickbook-tatkal-21a702cc/backend/api/serializers.py", "pattern": "/^    paid_via_wallet = serializers.BooleanField(read_only=True)$/", "language": "Python", "kind": "variable", "scope": "BookingSerializer", "scopeKind": "class"}, {"_type": "tag", "name": "preferred_berth", "path": "/home/kavia/workspace/code-generation/quickbook-tatkal-21a702cc/backend/api/serializers.py", "pattern": "/^    preferred_berth = serializers.CharField()$/", "language": "Python", "kind": "variable", "scope": "BookingSerializer", "scopeKind": "class"}, {"_type": "tag", "name": "user", "path": "/home/kavia/workspace/code-generation/quickbook-tatkal-21a702cc/backend/api/serializers.py", "pattern": "/^    user = serializers.StringRelatedField(read_only=True)$/", "language": "Python", "kind": "variable", "scope": "UserProfileSerializer", "scopeKind": "class"}, {"_type": "tag", "name": "user_profile", "path": "/home/kavia/workspace/code-generation/quickbook-tatkal-21a702cc/backend/api/serializers.py", "pattern": "/^    user_profile = UserProfileSerializer(read_only=True)$/", "language": "Python", "kind": "variable", "scope": "BookingSerializer", "scopeKind": "class"}, {"_type": "tag", "name": "user_profile_id", "path": "/home/kavia/workspace/code-generation/quickbook-tatkal-21a702cc/backend/api/serializers.py", "pattern": "/^    user_profile_id = serializers.PrimaryKeyRelatedField($/", "language": "Python", "kind": "variable", "scope": "BookingSerializer", "scopeKind": "class"}, {"_type": "tag", "name": "validate", "path": "/home/kavia/workspace/code-generation/quickbook-tatkal-21a702cc/backend/api/serializers.py", "pattern": "/^    def validate(self, data):$/", "language": "Python", "kind": "member", "signature": "(self, data)", "scope": "BookingSerializer", "scopeKind": "class"}, {"_type": "tag", "name": "wallet_balance", "path": "/home/kavia/workspace/code-generation/quickbook-tatkal-21a702cc/backend/api/serializers.py", "pattern": "/^    wallet_balance = serializers.DecimalField(max_digits=10, decimal_places=2, read_only=True)$/", "language": "Python", "kind": "variable", "scope": "UserProfileSerializer", "scopeKind": "class"}], "hash": "9d7dede2eb35ef4387fd5348600dce02", "format-version": 4, "code-base-name": "backend", "filename": "backend/api/serializers.py", "fields": [{"name": "booking = BookingSerializer(read_only=True)", "scope": "PaymentTransactionSerializer", "scopeKind": "class", "description": "unavailable"}, {"name": "booking_id = serializers.PrimaryKeyRelatedField(", "scope": "PaymentTransactionSerializer", "scopeKind": "class", "description": "unavailable"}, {"name": "fare = serializers.DecimalField(max_digits=8, decimal_places=2)", "scope": "BookingSerializer", "scopeKind": "class", "description": "unavailable"}, {"name": "fields = [", "scope": "BookingSerializer.Meta", "scopeKind": "class", "description": "unavailable"}, {"name": "model = Booking", "scope": "BookingSerializer.Meta", "scopeKind": "class", "description": "unavailable"}, {"name": "model = PaymentTransaction", "scope": "PaymentTransactionSerializer.Meta", "scopeKind": "class", "description": "unavailable"}, {"name": "model = UserProfile", "scope": "UserProfileSerializer.Meta", "scopeKind": "class", "description": "unavailable"}, {"name": "paid = serializers.BooleanField(read_only=True)", "scope": "BookingSerializer", "scopeKind": "class", "description": "unavailable"}, {"name": "paid_via_wallet = serializers.BooleanField(read_only=True)", "scope": "BookingSerializer", "scopeKind": "class", "description": "unavailable"}, {"name": "preferred_berth = serializers.CharField()", "scope": "BookingSerializer", "scopeKind": "class", "description": "unavailable"}, {"name": "user = serializers.StringRelatedField(read_only=True)", "scope": "UserProfileSerializer", "scopeKind": "class", "description": "unavailable"}, {"name": "user_profile = UserProfileSerializer(read_only=True)", "scope": "BookingSerializer", "scopeKind": "class", "description": "unavailable"}, {"name": "user_profile_id = serializers.PrimaryKeyRelatedField(", "scope": "BookingSerializer", "scopeKind": "class", "description": "unavailable"}, {"name": "wallet_balance = serializers.DecimalField(max_digits=10, decimal_places=2, read_only=True)", "scope": "UserProfileSerializer", "scopeKind": "class", "description": "unavailable"}]}